twitter_analysis_tools/__init__.py
twitter_analysis_tools/fileio.py
twitter_analysis_tools/plotting.py
twitter_analysis_tools/utils.py
twitter_analysis_tools/bin/__init__.py
twitter_analysis_tools/bin/my_example.py
twitter_analysis_tools/text/__init__.py
twitter_analysis_tools/text/_nltk_stopwords.py
twitter_analysis_tools/text/emojis.py
twitter_analysis_tools/text/ngrams.py
twitter_analysis_tools/text/stopwords.py
twitter_analysis_tools/twitter/__init__.py
twitter_analysis_tools/twitter/clean_text.py
twitter_analysis_tools/twitter/common_pipelines.py
twitter_analysis_tools/twitter/file_mgmt.py
twitter_analysis_tools/twitter/get_tweets.py
twitter_analysis_tools/twitter/tweet_info.py
twitter_analysis_tools/twitter/vocabulary.py
twitter_analysis_tools-0.0.1.dist-info/LICENSE
twitter_analysis_tools-0.0.1.dist-info/METADATA
twitter_analysis_tools-0.0.1.dist-info/WHEEL
twitter_analysis_tools-0.0.1.dist-info/entry_points.txt
twitter_analysis_tools-0.0.1.dist-info/top_level.txt
twitter_analysis_tools-0.0.1.dist-info/RECORD
