Metadata-Version: 2.1
Name: twitter-analysis-tools
Version: 0.0.1
Summary: Tools for loading, manipulating and filtering tweets.
Home-page: https://github.com/dmmolitor/twitter-analysis-tools
Author: Denali Molitor
Author-email: dmolitor14@gmail.com
License: MIT
Keywords: twitter_analysis_tools
Platform: UNKNOWN
Classifier: Development Status :: 2 - Pre-Alpha
Classifier: Intended Audience :: Science/Research 
Classifier: License :: OSI Approved :: MIT License
Classifier: Natural Language :: English
Classifier: Programming Language :: Python
Classifier: Programming Language :: Python :: 3
Classifier: Programming Language :: Python :: 3 :: Only
Classifier: Programming Language :: Python :: 3.6
Classifier: Programming Language :: Python :: 3.7
Classifier: Programming Language :: Python :: 3.8
Classifier: Topic :: Scientific/Engineering
Requires-Python: >=3.6
Requires-Dist: tqdm (>=4.45.0)
Requires-Dist: numpy (>=1.18.2)
Requires-Dist: nltk (>=3.4.5)
Requires-Dist: scikit-learn (>=0.22.2.post1)
Requires-Dist: loguru (>=0.4.1)
Requires-Dist: matplotlib (>=3.2.1)
Requires-Dist: seaborn (>=0.10.0)
Requires-Dist: demoji (==0.2.1)
Requires-Dist: scipy (>=1.4.1)
Requires-Dist: pyfunctional (>=1.3.0)
Requires-Dist: lazy-property (>=0.0.1)
Provides-Extra: all
Requires-Dist: tqdm (>=4.45.0) ; extra == 'all'
Requires-Dist: numpy (>=1.18.2) ; extra == 'all'
Requires-Dist: nltk (>=3.4.5) ; extra == 'all'
Requires-Dist: scikit-learn (>=0.22.2.post1) ; extra == 'all'
Requires-Dist: loguru (>=0.4.1) ; extra == 'all'
Requires-Dist: matplotlib (>=3.2.1) ; extra == 'all'
Requires-Dist: seaborn (>=0.10.0) ; extra == 'all'
Requires-Dist: demoji (==0.2.1) ; extra == 'all'
Requires-Dist: scipy (>=1.4.1) ; extra == 'all'
Requires-Dist: pyfunctional (>=1.3.0) ; extra == 'all'
Requires-Dist: lazy-property (>=0.0.1) ; extra == 'all'
Requires-Dist: pytest ; extra == 'all'
Requires-Dist: pytest-cov ; extra == 'all'
Requires-Dist: pytest-raises ; extra == 'all'
Requires-Dist: pytest-datadir ; extra == 'all'
Requires-Dist: sphinx (==1.8.5) ; extra == 'all'
Requires-Dist: sphinx-rtd-theme ; extra == 'all'
Requires-Dist: m2r ; extra == 'all'
Requires-Dist: pytest-runner ; extra == 'all'
Requires-Dist: pre-commit ; extra == 'all'
Requires-Dist: bump2version (>=1.0.0) ; extra == 'all'
Requires-Dist: ipython (>=7.5.0) ; extra == 'all'
Requires-Dist: tox (>=3.5.2) ; extra == 'all'
Requires-Dist: twine (>=1.13.0) ; extra == 'all'
Requires-Dist: wheel (>=0.33.1) ; extra == 'all'
Provides-Extra: dev
Requires-Dist: pytest ; extra == 'dev'
Requires-Dist: pytest-cov ; extra == 'dev'
Requires-Dist: pytest-raises ; extra == 'dev'
Requires-Dist: pytest-datadir ; extra == 'dev'
Requires-Dist: sphinx (==1.8.5) ; extra == 'dev'
Requires-Dist: sphinx-rtd-theme ; extra == 'dev'
Requires-Dist: m2r ; extra == 'dev'
Requires-Dist: pytest-runner ; extra == 'dev'
Requires-Dist: pre-commit ; extra == 'dev'
Requires-Dist: bump2version (>=1.0.0) ; extra == 'dev'
Requires-Dist: ipython (>=7.5.0) ; extra == 'dev'
Requires-Dist: tox (>=3.5.2) ; extra == 'dev'
Requires-Dist: twine (>=1.13.0) ; extra == 'dev'
Requires-Dist: wheel (>=0.33.1) ; extra == 'dev'
Provides-Extra: docs
Requires-Dist: sphinx (==1.8.5) ; extra == 'docs'
Requires-Dist: sphinx-rtd-theme ; extra == 'docs'
Requires-Dist: m2r ; extra == 'docs'
Provides-Extra: setup
Requires-Dist: pytest-runner ; extra == 'setup'
Provides-Extra: test
Requires-Dist: pytest ; extra == 'test'
Requires-Dist: pytest-cov ; extra == 'test'
Requires-Dist: pytest-raises ; extra == 'test'
Requires-Dist: pytest-datadir ; extra == 'test'
